hypast/Correct2Seg.py
hypast/CreateHDF5.py
hypast/HypothalamusDataset.py
hypast/MyModelLightning.py
hypast/Predictor.py
hypast/Preprocessing.py
hypast/Trainer.py
hypast/__init__.py
hypast/model.py
hypast-0.0.7.dist-info/LICENSE
hypast-0.0.7.dist-info/METADATA
hypast-0.0.7.dist-info/WHEEL
hypast-0.0.7.dist-info/top_level.txt
hypast-0.0.7.dist-info/RECORD
