Metadata-Version: 2.1
Name: hypast
Version: 0.0.7
Summary: Hypothalamus Automatic Segmentation Tool
Home-page: https://github.com/MICLab-Unicamp/HypAST
Author: Livia Rodrigues
Author-email: l180545@dac.unicamp.br
License: UNKNOWN
Platform: UNKNOWN
Classifier: Programming Language :: Python :: 3
Classifier: Operating System :: OS Independent
Classifier: License :: OSI Approved :: MIT License
Requires-Python: >3.7
Requires-Dist: numpy (==1.18.1)
Requires-Dist: pytorch-lightning (==1.4.7)
Requires-Dist: h5py (==2.10.0)
Requires-Dist: scikit-image (==0.17.2)
Requires-Dist: nibabel (==3.1.1)
Requires-Dist: connected-components-3d
Requires-Dist: albumentations (==0.4.6)
Requires-Dist: scikit-learn (==0.22.2.post1)
Requires-Dist: efficientnet-pytorch
